README.rst
setup.py
bin/wetransfer-download
bin/wetransfer-upload
wetransferpy/__init__.py
wetransferpy/wetransfer.py
wetransferpy.egg-info/PKG-INFO
wetransferpy.egg-info/SOURCES.txt
wetransferpy.egg-info/dependency_links.txt
wetransferpy.egg-info/requires.txt
wetransferpy.egg-info/top_level.txt