Metadata-Version: 1.1
Name: wetransferpy
Version: 0.1.6
Summary: WeTransfer command line utility.
Home-page: http://github.com/predat/wetransferpy
Author: Sylvain Maziere, Paul Delannoy
Author-email: sylvain@predat.fr, paul@highwaytv.com
License: MIT
Download-URL: https://github.com/predat/wetransferpy/tarball/0.1.6
Keywords: wetransfer upload download authenticate
Platform: UNKNOWN
Classifier: Development Status :: 3 - Alpha
Classifier: Intended Audience :: Developers
Classifier: Topic :: Software Development :: Build Tools
Classifier: License :: OSI Approved :: MIT License
Classifier: Programming Language :: Python :: 2.7
